MANIFEST.in
README.txt
setup.py
docs/HISTORY.txt
docs/LICENSE.txt
src/silva/__init__.py
src/silva.security.addables.egg-info/PKG-INFO
src/silva.security.addables.egg-info/SOURCES.txt
src/silva.security.addables.egg-info/dependency_links.txt
src/silva.security.addables.egg-info/namespace_packages.txt
src/silva.security.addables.egg-info/not-zip-safe
src/silva.security.addables.egg-info/requires.txt
src/silva.security.addables.egg-info/top_level.txt
src/silva/security/__init__.py
src/silva/security/addables/AddablesPermissions.gif
src/silva/security/addables/AddablesPermissions.py
src/silva/security/addables/__init__.py
src/silva/security/addables/configure.zcml
src/silva/security/addables/ftesting.zcml
src/silva/security/addables/AddablesPermissions_templates/configurepermissions.cpt
src/silva/security/addables/AddablesPermissions_templates/managepermissions.pt
src/silva/security/addables/tests/__init__.py
src/silva/security/addables/tests/test_service.py