Metadata-Version: 1.1
Name: silva.security.addables
Version: 3.0.2
Summary: Configure which content type is addable for which Silva roles
Home-page: https://github.com/silvacms/silva.security.addables
Author: Sylvain Viollon
Author-email: info@infrae.com
License: BSD
Keywords: silva roles security
Platform: UNKNOWN
Classifier: Framework :: Zope2
Classifier: Programming Language :: Python
Classifier: Topic :: Software Development :: Libraries :: Python Modules
Classifier: License :: OSI Approved :: BSD License
